[
  {
    "cuda": {
      "major": 12,
      "minor": 8
    },
    "minLinuxDriver": {
      "major": 570,
      "minor": 124,
      "patch": 6
    },
    "minWindowsDriver": {
      "major": 572,
      "minor": 61,
      "patch": 0
    }
  },
  {
    "cuda": {
      "major": 12,
      "minor": 6
    },
    "minLinuxDriver": {
      "major": 560,
      "minor": 35,
      "patch": 5
    },
    "minWindowsDriver": {
      "major": 561,
      "minor": 17,
      "patch": 0
    }
  },
  {
    "cuda": {
      "major": 12,
      "minor": 5
    },
    "minLinuxDriver": {
      "major": 555,
      "minor": 42,
      "patch": 6
    },
    "minWindowsDriver": {
      "major": 555,
      "minor": 85,
      "patch": 0
    }
  },
  {
    "cuda": {
      "major": 12,
      "minor": 4
    },
    "minLinuxDriver": {
      "major": 550,
      "minor": 54,
      "patch": 15
    },
    "minWindowsDriver": {
      "major": 551,
      "minor": 78,
      "patch": 0
    }
  },
  {
    "cuda": {
      "major": 12,
      "minor": 3
    },
    "minLinuxDriver": {
      "major": 545,
      "minor": 23,
      "patch": 8
    },
    "minWindowsDriver": {
      "major": 546,
      "minor": 12,
      "patch": 0
    }
  },
  {
    "cuda": {
      "major": 12,
      "minor": 2
    },
    "minLinuxDriver": {
      "major": 535,
      "minor": 104,
      "patch": 5
    },
    "minWindowsDriver": {
      "major": 537,
      "minor": 13,
      "patch": 0
    }
  },
  {
    "cuda": {
      "major": 12,
      "minor": 1
    },
    "minLinuxDriver": {
      "major": 530,
      "minor": 30,
      "patch": 2
    },
    "minWindowsDriver": {
      "major": 531,
      "minor": 14,
      "patch": 0
    }
  },
  {
    "cuda": {
      "major": 12,
      "minor": 0
    },
    "minLinuxDriver": {
      "major": 525,
      "minor": 85,
      "patch": 12
    },
    "minWindowsDriver": {
      "major": 528,
      "minor": 33,
      "patch": 0
    }
  },
  {
    "cuda": {
      "major": 11,
      "minor": 8
    },
    "minLinuxDriver": {
      "major": 520,
      "minor": 61,
      "patch": 5
    },
    "minWindowsDriver": {
      "major": 520,
      "minor": 6,
      "patch": 0
    }
  },
  {
    "cuda": {
      "major": 11,
      "minor": 7
    },
    "minLinuxDriver": {
      "major": 515,
      "minor": 48,
      "patch": 7
    },
    "minWindowsDriver": {
      "major": 516,
      "minor": 31,
      "patch": 0
    }
  },
  {
    "cuda": {
      "major": 11,
      "minor": 6
    },
    "minLinuxDriver": {
      "major": 510,
      "minor": 47,
      "patch": 3
    },
    "minWindowsDriver": {
      "major": 511,
      "minor": 65,
      "patch": 0
    }
  },
  {
    "cuda": {
      "major": 11,
      "minor": 5
    },
    "minLinuxDriver": {
      "major": 495,
      "minor": 29,
      "patch": 5
    },
    "minWindowsDriver": {
      "major": 496,
      "minor": 13,
      "patch": 0
    }
  },
  {
    "cuda": {
      "major": 11,
      "minor": 4
    },
    "minLinuxDriver": {
      "major": 470,
      "minor": 82,
      "patch": 1
    },
    "minWindowsDriver": {
      "major": 472,
      "minor": 50,
      "patch": 0
    }
  },
  {
    "cuda": {
      "major": 11,
      "minor": 3
    },
    "minLinuxDriver": {
      "major": 465,
      "minor": 19,
      "patch": 1
    },
    "minWindowsDriver": {
      "major": 465,
      "minor": 89,
      "patch": 0
    }
  },
  {
    "cuda": {
      "major": 11,
      "minor": 2
    },
    "minLinuxDriver": {
      "major": 460,
      "minor": 32,
      "patch": 3
    },
    "minWindowsDriver": {
      "major": 461,
      "minor": 33,
      "patch": 0
    }
  },
  {
    "cuda": {
      "major": 11,
      "minor": 1
    },
    "minLinuxDriver": {
      "major": 455,
      "minor": 32,
      "patch": 0
    },
    "minWindowsDriver": {
      "major": 456,
      "minor": 81,
      "patch": 0
    }
  },
  {
    "cuda": {
      "major": 11,
      "minor": 0
    },
    "minLinuxDriver": {
      "major": 450,
      "minor": 51,
      "patch": 6
    },
    "minWindowsDriver": {
      "major": 451,
      "minor": 82,
      "patch": 0
    }
  },
  {
    "cuda": {
      "major": 10,
      "minor": 2
    },
    "minLinuxDriver": {
      "major": 440,
      "minor": 33,
      "patch": 0
    },
    "minWindowsDriver": {
      "major": 441,
      "minor": 22,
      "patch": 0
    }
  },
  {
    "cuda": {
      "major": 10,
      "minor": 1
    },
    "minLinuxDriver": {
      "major": 418,
      "minor": 39,
      "patch": 0
    },
    "minWindowsDriver": {
      "major": 418,
      "minor": 96,
      "patch": 0
    }
  },
  {
    "cuda": {
      "major": 10,
      "minor": 0
    },
    "minLinuxDriver": {
      "major": 410,
      "minor": 48,
      "patch": 0
    },
    "minWindowsDriver": {
      "major": 411,
      "minor": 31,
      "patch": 0
    }
  },
  {
    "cuda": {
      "major": 9,
      "minor": 2
    },
    "minLinuxDriver": {
      "major": 396,
      "minor": 37,
      "patch": 0
    },
    "minWindowsDriver": {
      "major": 398,
      "minor": 26,
      "patch": 0
    }
  },
  {
    "cuda": {
      "major": 9,
      "minor": 1
    },
    "minLinuxDriver": {
      "major": 390,
      "minor": 46,
      "patch": 0
    },
    "minWindowsDriver": {
      "major": 391,
      "minor": 29,
      "patch": 0
    }
  },
  {
    "cuda": {
      "major": 9,
      "minor": 0
    },
    "minLinuxDriver": {
      "major": 384,
      "minor": 81,
      "patch": 0
    },
    "minWindowsDriver": {
      "major": 385,
      "minor": 54,
      "patch": 0
    }
  },
  {
    "cuda": {
      "major": 8,
      "minor": 0
    },
    "minLinuxDriver": {
      "major": 375,
      "minor": 26,
      "patch": 0
    },
    "minWindowsDriver": {
      "major": 376,
      "minor": 51,
      "patch": 0
    }
  },
  {
    "cuda": {
      "major": 7,
      "minor": 5
    },
    "minLinuxDriver": {
      "major": 352,
      "minor": 31,
      "patch": 0
    },
    "minWindowsDriver": {
      "major": 353,
      "minor": 66,
      "patch": 0
    }
  },
  {
    "cuda": {
      "major": 7,
      "minor": 0
    },
    "minLinuxDriver": {
      "major": 346,
      "minor": 46,
      "patch": 0
    },
    "minWindowsDriver": {
      "major": 347,
      "minor": 62,
      "patch": 0
    }
  }
]
